{
  "id": "pg_0968e736",
  "chapterOrder": 6,
  "title": "生成模型：自编码器与生成对抗网络",
  "status": "ready",
  "blocks": [
    {
      "id": "4b2f26f0dccd",
      "type": "section",
      "status": "ready",
      "params": {
        "title": "生成模型：自编码器与生成对抗网络",
        "subtitle": "从降维重构到对抗生成",
        "contentType": "concept",
        "focus": "章节概述与学习路径"
      },
      "payload": {
        "content": "## 章节概述\n\n本章将深入探讨生成模型领域中的两大经典范式——**自编码器（Autoencoders）**与**生成对抗网络（Generative Adversarial Networks，简称GANs）**。这两类模型均属于无监督或半监督学习的范畴，其核心目标是从数据中学习潜在的分布规律，从而生成新的、与训练数据相似的样本。\n\n自编码器是一种基于编码-解码结构的模型。它通过一个编码器（Encoder）将输入数据压缩到低维的潜在空间（latent space），再通过一个解码器（Decoder）尽可能还原原始数据。这种结构使得自编码器能够学习到数据的紧凑表示（representation），广泛应用于数据压缩、降噪、异常检测以及特征提取等任务。例如，在图像处理中，自编码器可以去除噪声，提取出图像最本质的结构特征。\n\n生成对抗网络则由两个神经网络相互博弈组成：生成器（Generator）负责从随机噪声中生成假样本，判别器（Discriminator）则尝试区分真样本与假样本。在训练过程中，两者通过零和游戏般的对抗不断优化：生成器试图欺骗判别器，而判别器则努力提高辨别能力。最终，生成器能够产生与真实数据分布几乎无法区分的样本，例如生成高分辨率的逼真人脸图像或艺术作品。\n\n本章将系统对比自编码器与生成对抗网络在**原理、训练方式、优缺点及应用场景**上的差异。自编码器训练稳定，易于收敛，但生成样本的多样性可能受限；GANs生成的样本质量极高，但训练过程容易不稳定，出现模式坍塌等问题。通过对比，读者将理解何时选择自编码器，何时更适合使用GANs，以及如何根据具体任务进行模型设计。\n\n## 学习路径\n\n为了高效掌握这两类模型，建议读者按照以下路径进行学习，并结合实际编程实践巩固理解。\n\n### 先修知识\n\n在进入本章之前，需要具备以下基础：\n- **神经网络基础**：理解多层感知机、激活函数、损失函数及梯度下降等概念。\n- **反向传播算法**：掌握神经网络中梯度计算的链式法则，这是所有深度学习模型训练的核心。\n- **概率分布与最大似然估计**：了解概率密度函数、条件概率、KL散度等概念，以及如何通过最大似然估计来优化模型参数。这对于理解变分自编码器和GAN的损失函数至关重要。\n\n### 建议学习步骤\n\n建议按照从简单到复杂、从稳健到进阶的顺序进行学习：\n\n1.  **自编码器系列**：\n    - **标准自编码器**：首先实现一个最简单的三层神经网络自编码器，理解编码-解码的基本流程和压缩表示的含义。在MNIST手写数字数据集上进行训练，观察重建效果。\n    - **变分自编码器（VAE）**：在理解标准自编码器后，学习变分自编码器的核心思想——将潜在空间变为连续的、带约束的概率分布。掌握重参数化技巧（reparameterization trick）和KL散度项的作用。VAE训练稳定，且能生成具有一定多样性的新样本。\n\n2.  **生成对抗网络系列**：\n    - **基础GAN**：理解生成器和判别器交替训练的模式，以及针对极小化极大值（minimax）目标函数的实现。注意训练不平衡问题（如判别器收敛过快）。\n    - **深度卷积生成对抗网络（DCGAN）**：学习如何将卷积神经网络（CNN）引入GAN，提升图像生成的稳定性与分辨率。掌握批归一化、反卷积层等关键技巧。\n    - **Wasserstein GAN（WGAN）**：针对原始GAN训练不稳定的问题，学习WGAN通过引入Wasserstein距离作为优化目标，并引入梯度惩罚（WGAN-GP）来强制模型满足Lipschitz约束。这是实际应用中最常用的变体之一。\n\n### 实践环节\n\n- **框架选择**：推荐使用TensorFlow（Keras API）或PyTorch进行实现。两者均有丰富的官方教程和社区资源。\n- **数据集**：从简单的MNIST（手写数字）和CIFAR-10（自然图像）入手。这些数据集规模适中，便于快速迭代实验。\n- **实验任务**：\n    - 实现一个全连接的自编码器用于MNIST图像重建。\n    - 实现VAE并观察潜在空间的连续插值效果（例如，在两幅人脸图像之间生成平滑过渡）。\n    - 实现DCGAN生成MNIST或CIFAR-10的图像，观察生成质量随训练轮次的变化。\n    - 对比WGAN与基础GAN在训练过程中的稳定性差异。\n\n### 延伸阅读\n\n在掌握基础后，建议探索以下前沿方向，进一步拓展视野：\n- **条件生成模型**：学习条件变分自编码器（cVAE）和条件GAN（cGAN），它们允许在生成过程中引入控制条件（如类别标签或属性描述），从而生成特定类别的样本。\n- **自编码器与GAN的结合**：如对抗自编码器（AAE）将VAE的潜在空间正则化替换为GAN的对抗损失，双向生成对抗网络（BiGAN）则同时学习从数据到潜在空间的映射。这些模型融合了两者的优势，兼具自编码器的表示学习能力和GAN的生成逼真度。\n\n通过以上路径的学习，读者不仅能够深刻理解自编码器与生成对抗网络的原理，更能通过实践掌握它们的实现与调试技巧，为后续研究更先进的生成模型奠定坚实基础。",
        "outline": {
          "sections": [
            {
              "heading": "章节概述",
              "points": [
                "本章聚焦于两种经典的无监督/半监督生成模型：自编码器（Autoencoders）与生成对抗网络（GANs）",
                "自编码器通过编码-解码结构学习数据的紧凑表示，可用于数据压缩、降噪与特征提取",
                "生成对抗网络由生成器与判别器博弈训练，擅长生成逼真的新样本",
                "本章将对比两者的原理、训练方式、优缺点及应用场景"
              ]
            },
            {
              "heading": "学习路径",
              "points": [
                "先修知识：掌握神经网络基础、反向传播、概率分布与最大似然估计",
                "建议步骤：先学习自编码器（标准自编码器→变分自编码器VAE），再转向生成对抗网络（基础GAN→DCGAN→WGAN）",
                "实践环节：使用TensorFlow或PyTorch实现简单的自编码器和GAN，在MNIST/CIFAR-10数据集上训练",
                "延伸阅读：条件生成模型（cVAE、cGAN）、自编码器与GAN的结合（如AAE、BiGAN）"
              ]
            }
          ]
        }
      },
      "sourceAnchors": [],
      "metadata": {
        "wordCount": 2178,
        "sectionCount": 2
      }
    },
    {
      "id": "96203fffe74d",
      "type": "text",
      "status": "ready",
      "params": {
        "depth": "introductory",
        "focus": "生成模型的核心问题：学习数据分布，从高维数据中提取潜在特征，并生成新样本。对比自编码器（重构）与GAN（对抗）的哲学差异。"
      },
      "payload": {
        "content": "在机器学习的广阔领域中，生成模型的目标是让机器学会创造。这不仅仅是对已有数据的简单复制，而是理解数据背后的隐藏规律，然后“无中生有”地生成全新的、合理的样本。核心问题可以概括为三步：首先，从复杂的高维数据（如图像、文本）中提取最具代表性的低维潜在特征；其次，掌握这些特征在潜在空间中的分布规律；最后，从这个分布中采样，并解码回数据空间，生成新样本。自编码器与生成对抗网络就是这一使命下最经典的两条路径。\n\n**自编码器：始于重构的“瘦身”哲学**\n\n自编码器采用一种“自我压缩”的思路。它由一个编码器和一个解码器组成。就像给一张照片拍一张非常小的缩略图，再试图从缩略图恢复出原图。整个过程追求的是“重构误差最小化”。当模型能完美还原输入时，意味着那张“缩略图”（即潜在特征）已经抓住了原始数据最核心的信息。这是一种内向、诚实的哲学：它关心的不是“这个样本看起来像真的吗”，而是“我恢复出来的和原来的像吗”。因此，自编码器擅长无监督的特征提取与数据降维，但它生成的样本往往偏向模糊，因为它倾向于学习数据分布的平均值，而非细节的精确纹理。\n\n**生成对抗网络：在博弈中走向真实的“对抗”哲学**\n\n生成对抗网络开辟了一条截然不同的道路，引入了“对抗”的游戏。它包含两个角色：一个生成器，试图凭空制造以假乱真的样本；一个判别器，试图分辨输入是来自真实数据还是生成器的赝品。生成器的目标是“蒙骗”判别器，而判别器的目标是“不被骗”。两者在零和博弈中共同进化。当判别器最终无法分辨真伪时，生成器就掌握了真实数据的分布。这种哲学是外向、竞争的：它不直接追求重构的精确性，而是通过对抗压力，迫使生成器捕捉数据的高频细节和锐利边缘，从而生成肉眼看来更逼真的样本。但其代价是训练不稳定，且容易丢失数据全局的多样性（模式坍塌）。\n\n**哲学差异的核心：重构 vs. 对抗**\n\n自编码器与GAN的哲学差异，本质上是“还原”与“欺骗”的区别。自编码器追求的是“忠实”，它像一位严谨的考古学家，力求通过碎片完整复原文物，但在精细纹理（如头发、笔触）上往往力不从心。GAN追求的是“逼真”，它像一位技艺高超的赝品画师，在和鉴定专家（判别器）的反复博弈中，磨炼出足以乱真的笔法，但有可能为了应付专家而只学会画某几种最“像”的图案，丧失整体风格多样性。理解了这一点，就理解了两种模型在生成质量、模式覆盖和训练稳定性上为何有着天然的权衡。"
      },
      "sourceAnchors": [],
      "metadata": {
        "wordCount": 1003,
        "transitionIn": "在深度学习中，如何让机器学会创造？本章将探索两种经典范式：自编码器与生成对抗网络。"
      }
    },
    {
      "id": "b08c6c735474",
      "type": "callout",
      "status": "ready",
      "params": {
        "calloutType": "idea",
        "highlight": "类比思考",
        "focus": "关键比喻：自编码器像'压缩-解压'过程，GAN像'画家与鉴赏家'的博弈。"
      },
      "payload": {
        "content": "💡 **关键比喻**  \n自编码器如同“压缩-解压”过程：先将数据编码为紧凑的潜在表示，再解码还原。而生成对抗网络则是“画家与鉴赏家”的博弈：生成器（画家）试图伪造逼真样本，判别器（鉴赏家）努力区分真伪，两者对抗训练中共同提升。",
        "calloutType": "idea"
      },
      "sourceAnchors": [],
      "metadata": {
        "transitionIn": "理解这两种模型，可以先从两个生活中的类比入手："
      }
    },
    {
      "id": "51b6e1a90dfe",
      "type": "text",
      "status": "ready",
      "params": {
        "depth": "intermediate",
        "keyConcept": "自编码器（AE/VAE）",
        "focus": "自编码器原理：编码器降维（提取潜在编码z），解码器重构（重建原始输入）。引出变分自编码器（VAE）——从确定性编码到概率分布编码，引入KL散度。"
      },
      "payload": {
        "content": "自编码器是一种经典的无监督学习模型，其核心思想是通过神经网络学习数据的有效表示。它由两个主要部分组成：编码器和解码器。编码器将高维输入数据压缩到一个低维的潜在空间，提取出关键特征，这个低维表示通常称为潜在编码z。例如，一张高分辨率图片可能包含数万个像素点，编码器可以将其压缩为几十或几百个数值，这些数值代表了图片的核心信息。解码器则负责从这个压缩表示中重建出与原始输入尽可能相似的输出。通过训练使得输出和输入之间的差异最小化，自编码器就学会了如何捕捉数据的内在结构。\n\n然而，传统自编码器存在一个局限：解码器得到的潜在编码z是确定性的，即对于同一个输入，编码器总是输出一个固定的点。这种确定性的表示往往缺乏泛化能力，在生成新数据时效果不佳。比如，如果我们希望从潜在空间中随机采样来生成新的图片，传统自编码器无法保证采样点对应于有意义的输出。\n\n为了解决这一问题，变分自编码器（VAE）引入了关键改进：它将编码过程从输出一个确定性的数值改为输出一个概率分布。具体来说，编码器不再直接输出潜在编码z，而是输出一个分布参数（通常是均值和方差）。这样，潜在编码z就从确定性的点变成了一个随机变量，可以从对应的概率分布中采样得到。这种概率化的编码方式使得模型能够更好地捕捉数据的整体结构，并且具备生成能力。\n\n为了实现这种概率分布编码，VAE在训练中引入了KL散度（Kullback-Leibler散度）。KL散度衡量了两个概率分布之间的差异。在VAE中，它被用来约束编码器输出的分布尽可能接近一个先验分布（通常是标准正态分布）。这样，潜在空间就具有了良好的结构——相似的编码会聚集在一起，不同类别的编码会自然分 离，使得从潜在空间中随机采样能生成合理的新数据。通过结合重构误差和KL散度作为总损失函数，VAE不仅学会了压缩和重建数据，还学会了生成连贯且多样化的新样本。"
      },
      "sourceAnchors": [],
      "metadata": {
        "wordCount": 780,
        "transitionIn": "首先看自编码器如何实现'压缩与还原'。"
      }
    },
    {
      "id": "6bd78771b5ef",
      "type": "concept_graph",
      "status": "ready",
      "params": {
        "graphType": "comparison",
        "nodes": [
          "输入",
          "编码器",
          "潜在空间",
          "解码器",
          "输出（重构）",
          "生成器",
          "判别器",
          "真实数据",
          "生成数据"
        ],
        "edges": [
          {
            "from": "输入",
            "to": "编码器",
            "label": "AE/VAE"
          },
          {
            "from": "编码器",
            "to": "潜在空间",
            "label": "AE: 单个向量 ; VAE: 分布参数"
          },
          {
            "from": "潜在空间",
            "to": "解码器",
            "label": ""
          },
          {
            "from": "解码器",
            "to": "输出（重构）"
          },
          {
            "from": "噪声",
            "to": "生成器",
            "label": "GAN"
          },
          {
            "from": "生成器",
            "to": "生成数据"
          },
          {
            "from": "生成数据",
            "to": "判别器",
            "label": "假样本"
          },
          {
            "from": "真实数据",
            "to": "判别器",
            "label": "真样本"
          }
        ],
        "focus": "对比自编码器（AE）、变分自编码器（VAE）、生成对抗网络（GAN）的结构差异：AE（编码器-解码器），VAE（编码器输出均值/方差 - 采样 - 解码器），GAN（生成器 + 判别器对抗）。"
      },
      "payload": {
        "mermaid": "graph TD\n  A[\"No concepts defined\"]\n",
        "nodeCount": 0,
        "edgeCount": 0
      },
      "sourceAnchors": [],
      "metadata": {
        "transitionIn": "下图直观对比三种模型的结构差异："
      }
    },
    {
      "id": "2e8607e7cc6a",
      "type": "text",
      "status": "ready",
      "params": {
        "depth": "intermediate",
        "keyConcept": "GAN与纳什均衡",
        "focus": "生成对抗网络（GAN）核心：生成器G从噪声生成假数据，判别器D区分真假。二者进行极小极大博弈，达到纳什均衡。训练技巧（如交替训练、模式坍塌）。"
      },
      "payload": {
        "content": "生成对抗网络（Generative Adversarial Network，简称GAN）是生成模型领域的一项革命性突破，由Ian Goodfellow于2014年提出。其核心思想源于一个巧妙的博弈过程：网络由两个相互对抗的模块组成——生成器（Generator，简称G）和判别器（Discriminator，简称D）。\n\n生成器的任务是从随机噪声中“无中生有”，生成尽可能逼真的假数据。这些噪声通常服从高斯分布或均匀分布，通过生成器的多层神经网络变换，转化为与真实数据分布相似的样本——比如图像、文本或音频。而判别器则像一位挑剔的鉴定专家，它的目标是准确分辨输入数据是来自真实数据集，还是由生成器编造的假货。\n\n这两个网络在训练中展开一场零和博弈：生成器努力提升造假水平，让判别器难以分辨；判别者则不断强化鉴别能力，避免被欺骗。这种对抗关系可以用一个极小极大博弈（Minimax Game）来描述：生成器试图最小化判别器正确分辨的概率，而判别器则试图最大化这个概率。最终，理想的结果是达到纳什均衡——此时生成器生成的数据分布与真实数据分布完全一致，判别器的准确率停留在50%，无论输入真假，它都无法区分。\n\n然而，GAN的训练并不容易，需要精细的技巧。最常见的做法是交替训练：每次迭代中，先固定生成器，更新判别器，使其更好地区分真假；然后固定判别器，更新生成器，根据判别器的反馈改进造假质量。这种交替更新可以防止某一方过强，导致网络崩溃。\n\n一个典型的难题是模式坍塌（Mode Collapse），即生成器只学会生成少数几种样式的数据，缺乏多样性。例如，生成人脸图像时，它可能只输出同一种表情和角度。为了解决模式坍塌，研究者提出了多种改进，比如使用不同的损失函数、引入小批量判别（Mini-batch Discrimination）或采用惩罚项鼓励生成器覆盖更多模式。\n\n总之，GAN通过动态博弈和精巧的训练策略，在图像生成、风格迁移、超分辨率等任务中展现了惊人的创造力。理解其核心机制——生成器与判别器的对抗、交替训练的技巧以及模式坍塌的应对——是掌握这一强大模型的关键。"
      },
      "sourceAnchors": [],
      "metadata": {
        "wordCount": 887,
        "transitionIn": "如果说自编码器追求'还原真实'，GAN则追求'以假乱真'。"
      }
    },
    {
      "id": "e80ae64d51d5",
      "type": "callout",
      "status": "ready",
      "params": {
        "calloutType": "pitfall",
        "highlight": "GAN训练陷阱",
        "focus": "训练要点总结：GAN训练不稳定（模式坍塌、梯度消失）的常见原因与缓解方案（如Wasserstein距离、标签平滑）。"
      },
      "payload": {
        "content": "⚠️ 常见陷阱：GAN训练不稳定  \n模式坍塌和梯度消失是GAN训练的两大核心难题。模式坍塌源于生成器过度拟合少数样本，而梯度消失多因判别器过强或损失函数设计不当。缓解方案包括使用Wasserstein距离替代JS散度改善梯度流，以及应用标签平滑防止判别器过度自信。",
        "calloutType": "pitfall"
      },
      "sourceAnchors": [],
      "metadata": {
        "transitionIn": "⚠️ 实践中的关键提醒："
      }
    },
    {
      "id": "9ed16d36720e",
      "type": "quiz",
      "status": "ready",
      "params": {
        "difficulty": "medium",
        "questionCount": 4,
        "topics": [
          "自编码器结构",
          "VAE的变分特性",
          "GAN的损失函数",
          "纳什均衡条件"
        ],
        "focus": "检测对自编码器降维/重构原理、VAE与AE的区别、GAN对抗机制和纳什均衡的理解。"
      },
      "payload": {
        "question": "在生成对抗网络（GAN）中，生成器（G）和判别器（D）的对抗训练最终达到的平衡状态是：",
        "options": [
          "A) 生成器完全模仿真实数据分布，判别器输出恒为1",
          "B) 生成器输出数据分布等于真实数据分布，判别器输出恒为0.5",
          "C) 判别器总能准确区分真假数据，生成器无法改进",
          "D) 生成器与判别器的损失同时降为0"
        ],
        "correctIndex": 1,
        "explanation": "GAN的纳什均衡要求生成器与判别器达到博弈均衡：生成器的数据分布等于真实数据分布（p_g = p_data），判别器无法区分真假（D(x)=0.5对所有x成立）。选项A中判别器恒为1意味着判别器被欺骗，不是均衡；选项C中判别器准确区分是生成器失败；选项D中损失降为0不可能同时满足（判别器损失为0时生成器损失无穷大）。"
      },
      "sourceAnchors": [],
      "metadata": {
        "difficulty": "medium",
        "transitionIn": "下面通过几个问题检验你的理解："
      }
    },
    {
      "id": "87bfb1ec7bcb",
      "type": "flash_cards",
      "status": "ready",
      "params": {
        "termCount": 8,
        "direction": "term-to-definition",
        "depth": "essential",
        "focus": "核心术语记忆：编码器、解码器、潜在空间、KL散度、生成器、判别器、纳什均衡、模式坍塌。"
      },
      "payload": {
        "cards": [
          {
            "front": "编码器",
            "back": "在自编码器中，编码器是一个神经网络，它接收输入数据（如一张图片）并将其压缩成一个低维的潜在空间表示（即编码）。这个过程旨在提取数据的关键特征，去除冗余信息，以便解码器能基于该表示重建原始数据。编码器通常由若干卷积层或全连接层构成，输出是一个向量。",
            "hint": "压缩输入"
          },
          {
            "front": "潜空间",
            "back": "潜在空间是数据压缩后的低维表示空间，其中每个点对应一个编码向量。在自编码器中，解码器从这个空间采样以重建数据；在生成对抗网络中，生成器通常从一个已知的潜空间（如高斯分布）中采样，通过逆映射生成新样本。潜空间的质量决定生成效果，其结构应具有连续性和有意义的语义。",
            "hint": "低维表示"
          },
          {
            "front": "KL散度",
            "back": "KL散度（Kullback-Leibler divergence）是衡量两个概率分布P和Q差异的非对称度量。在变分自编码器中，KL散度用于约束编码器输出的潜变量分布（通常是高斯）与标准正态分布接近，从而正则化潜空间，使生成样本更连续可信。公式为KL(P||Q)=∫P(x)log(P(x)/Q(x))dx。",
            "hint": "分布差异"
          },
          {
            "front": "生成器",
            "back": "在生成对抗网络中，生成器是一个神经网络，它接收随机噪声（如从高斯分布采样）作为输入，试图输出逼真的假数据（如图像），以欺骗判别器。其目标是通过学习真实数据的分布，生成与真实样本难以区分的新样本。训练中生成器不断提升，使判别器无法准确判断真假。",
            "hint": "假数据制造者"
          },
          {
            "front": "模式坍塌",
            "back": "模式坍塌是生成对抗网络中常见的失败模式，指生成器只生成少数几种“安全”的样本（比如只知道生成狗的图片，而忽略了猫、鸟等其他类别），从而失去多样性。这通常是因为生成器找到了对抗判别器的最优捷径，导致模型无法覆盖完整数据分布。解决策略包括使用改进的训练方法（如小批量特征匹配）或架构（如WGAN）。",
            "hint": "多样性丧失"
          }
        ]
      },
      "sourceAnchors": [],
      "metadata": {
        "cardCount": 5,
        "transitionIn": "最后，用闪卡巩固本章关键概念："
      }
    }
  ],
  "links": [],
  "metadata": {}
}